rgtestpython/__init__.py
rgtestpython/rg.py
rgtestpython/sunflower.py
rgtestpython/test.py
rgtestpython/tree.py
rgtestpython-2.1.dist-info/LICENSE.txt
rgtestpython-2.1.dist-info/METADATA
rgtestpython-2.1.dist-info/WHEEL
rgtestpython-2.1.dist-info/top_level.txt
rgtestpython-2.1.dist-info/RECORD
