Metadata-Version: 2.1
Name: rgtestpython
Version: 2.1
Summary: 测试python包
Author: rongge
Author-email: 78380834@qq.com
Classifier: Programming Language :: Python :: 3
Requires-Python: >=3
License-File: LICENSE.txt
Requires-Dist: pillow
